JVM이 다양한 플랫폼을 지원하고, 모든 VM이 동일한 프로그램 저장 형식을 지원한다는 것이 '플랫폼 독립성'의 핵심이다.
즉, VM과 바이트 코드 저장 형식이 여러 플랫폼에 구애 받지 않게 만드는 핵심이다.

자바 기술은 설계 초기부터 VM이 다른 언어를 실행할 가능성을 염두에 뒀다. 
그렇기에 JVM은 자바를 포함한 어떠한 언어에도 종속되지 않는다.
'클래스 파일'이란 특정한 바이너리 파일 형식에만 의존할 뿐이다.  
또한 클래스 파일을 이루는 바이트 코드 형식은 튜링 완전하므로 JVM에서 어떠한 언어도 표현할 수 있도록 보장한다.
더불어 자바 언어에서 효과적으로 표현하지 못하는 개념도 바이트 코드에서는 효과적으로 표현할 수 있다. 

# 1. 개요
자바 기술의 하위 호환성이 잘 유지되는 가장 큰 이유는 **안정적인 클래스 파일 구조**다. 
이번 장에서 설명할 클래스 파일 구조 대부분은 자바 가상 머신 명세 1판(1997) 내용 그대로다. (기본 구조는 거의 그대로다.)

클래스 파일은 동적으로 생성되어 클래스 로더에 직접 제공할 수도 있기 때문에 꼭 디스크에 파일 형태로 저장될 필요가 없다.
그래서 이번 장에서 말하는 클래스 파일 '구조'는 사실 클래스 파일 '형식'이라고 표현하는 것이 맞다.

![[JVM 6장 - 클래스 파일 구조.jpg|500]]
클래스 파일은 바이트를 하나의 단위로 하는 이진 스트림 집합체다. 
1바이트가 넘는 데이터는 바이트 단위로 분할 되며, 큰 단위의 바이트가 먼저 저장되는 빅 엔디언 방식으로 표현된다.
클래스 파일에 데이터를 저장할 때 의사 구조를 이용하는데, 이 구조엔 '부호 없는 숫자', '테이블'이라는 두 가지 데이터 타입만 존재한다.
- **부호 없는 숫자** 
	- 기본 데이터 타입을 표현하며, u1/u2/u4/u8이 있다. 각각 1, 2, 4, 8바이트를 의미한다.
	- 숫자, 인덱스 참조, 수량 값을 기술하거나 UTF-8로 인코딩된 문자열 값을 구성
- **테이블**
	- 여러 개의 부호 없는 숫자나 또 다른 테이블로 구성된 복합 데이터 타입을 표현
	- 이름은 관례적으로 \_info로 끝남
같은 타입의 데이터 여러 개를 표현할 때 그 개수가 정해져 있지 않다면 개수를 알려 주는 타입이 바로 앞에 등장한다.(* \_count  형태)
위 그림에 나온 데이터 항목은 **데이터가 저장되는 바이트 순서, 각 바이트의 의미, 길이, 순서가 모두 엄격하게 제한되며 변경될 수 없다**.

>[!NOTE]
>**빅 엔디언 방식 vs 리틀 엔디언 방식**
>빅 엔디언 방식은 큰 단위의 바이트가 먼저 저장되는 것을 의미한다. 때문에 낮은 메모리 주소에 저장된다. 즉, 가장 중요한 바이트를 먼저 저장하는 방식이다.
>이 방식은 사람이 숫자를 읽는 방식과 유사하며, 바이트를 배열처럼 취급할 때 적합하다.
>리틀 엔디언 방식은 빅 엔디언 방식의 반대며, 물리적으로 데이터를 조작하거나 산술 연산을 수행할 때 유리하다. 

# 2. 매직 넘버와 클래스 파일의 버전
모든 클래스 파일의 처음 4바이트는 **매직 넘버로 시작**한다. 이는 **VM이 허용하는 클래스 파일인지를 검증하는 용도**다.
파일 확장자는 사용자에 의해 변경될 수 있지만 매직넘버는 그렇지 않아 많은 곳에서 사용된다.(JPEG, GIF 등)
![[JVM 6장 - 클래스 파일 바이트 코드.png|700]]
매직 넘버 다음 4바이트는 클래스 파일의 버전 번호다. 5, 6번째는 마이너 버전을, 7, 8번째는 메이저 버전을 의미한다. 
상위 버전 JDK는 하위 버전을 인식할 수 있지만 그 반대는 안된다.
JDK 1.2부터는 마이너 버전을 사용하지 않는다. 자세한 버전 정보는 294p를 확인하자. 

# 3. 상수 풀
버전 번호 다음은 상수 풀 항목이다. **상수 풀은 클래스 파일의 자원 창고**라 할 수 있다. 때문에 공간이 대체로 가장 크다.
상수의 수는 고정적이지 않으므로 개수를 표현하기 위한 u2 타입의 데이터가 필요하다. 관례상 이 개수를 셀 때는 1부터 시작한다.(상수 풀만 해당)
**0번째를 비운 이유는 상수 풀 인덱스를 가리키는 데이터에서 '상수 풀 항목을 참조하지 않음'을 표현**해야 하기 때문이다.

상수 풀에 담기는 상수 유형은 리터럴과 심벌 참조 두 가지다. 
심벌 참조는 컴파일 관련 개념으로 아래와 같이 세분화할 수 있다.
- 모듈에서 export하거나 import하는 패키지
- 클래스와 인터페이스의 완전한 이름
- 필드 이름과 서술자
- 메서드 이름과 서술자
- 메서드 핸들과 메서드 타입
- 동적으로 계산되는 호출 사이트와 동적으로 계산되는 상수

>[!NOTE]
>**C/C++과 달리 Java에선 컴파일 시 링크 단계가 없다?**
>링크 단계는 함수와 같은 개체들을 메모리에 배치하는 것을 뜻한다. 즉, C/C++은 컴파일시 모든 함수와 변수의 메모리 위치가 결정된다.
>Java는 클래스를 로드할 때 동적으로 링크를 한다. 그렇기에 **Java의 필드, 메서드에 대한 메모리 구조는 클래스 파일에 저장되지 않는다.**

![[JVM 6장 - 상수 풀의 항목 타입.png|500]]
상수 풀 안의 상수 각각이 모두 테이블이다. 초기엔 11가지였으나 JDK21 기준 17가지로 늘어났다. 
각 타입의 테이블들은 공통적으로 u1 타입의 플래그 비트로 시작하며, 현재 상수가 속한 타입을 나타낸다. 
상수 풀이 가장 복잡한 데이터인 이유는 17가지 각각의 데이터 구조가 독립적이기 때문이다. 
각 상수 풀의 일반적인 구조는 301p를 참조

![[JVM 6장 - 상수풀 개수.png]]
책과는 달리 상수 풀의 개수가 0x0016으로 21개가 존재한다.

![[JVM 6장 - 상수 풀 구조.png|500]]
바이트 코드를 읽는 방법은 다음과 같다.
- 왼쪽부터 순차적으로 클래스 파일 구조를 읽는다.
- 첫 8바이트는 매직 넘버와 버전 표시다.
- 다음 u2타입의 2바이트는 상수 풀의 개수다.
- 이후 상수 풀의 구조에 따라 읽어 나간다.
- 이후 속성 테이블을 따라 읽어 나간다.

클래스 파일에서 메서드와 필드 등의 이름을 기술할 땐 CONSTANT_Utf8_info 타입 상수를 참조하는데, 이 상수의 최대 길이가 u2타입이므로 자바 메서드, 필드의 최대 길이는 65535로 제한된다.
그러므로 변수, 메서드 이름의 길이가 64KB를 넘으면 컴파일 되지 않는다.  

### javap로 출력한 상수 풀의 내용
```text
$ javap -verbose TestClass
public class chapter6.TestClass
  minor version: 0
  major version: 61
  flags: (0x0021) ACC_PUBLIC, ACC_SUPER
  this_class: #8                          // chapter6/TestClass
  super_class: #2                         // java/lang/Object
  interfaces: 0, fields: 1, methods: 2, attributes: 1
Constant pool:
   #1 = Methodref          #2.#3          // java/lang/Object."<init>":()V
   #2 = Class              #4             // java/lang/Object
   #3 = NameAndType        #5:#6          // "<init>":()V
   #4 = Utf8               java/lang/Object
   #5 = Utf8               <init>
   #6 = Utf8               ()V
   #7 = Fieldref           #8.#9          // chapter6/TestClass.m:I
   #8 = Class              #10            // chapter6/TestClass
   #9 = NameAndType        #11:#12        // m:I
  #10 = Utf8               chapter6/TestClass
  #11 = Utf8               m
  #12 = Utf8               I
  #13 = Utf8               Code
  #14 = Utf8               LineNumberTable
  #15 = Utf8               LocalVariableTable   => 책에는 없는 상수
  #16 = Utf8               this                 => 책에는 없는 상수.
  #17 = Utf8               Lchapter6/TestClass; => 책에는 없는 상수. 내부 이름을 의미(JVM이 해당 클래스가 속한 패키지를 찾기 위해. 리플렉션에서 사용하기 위함?)
  #18 = Utf8               inc
  #19 = Utf8               ()I
  #20 = Utf8               SourceFile
  #21 = Utf8               TestClass.java
{
  public chapter6.TestClass();
    descriptor: ()V
    flags: (0x0001) ACC_PUBLIC
    Code:
      stack=1, locals=1, args_size=1
         0: aload_0
         1: invokespecial #1                  // Method java/lang/Object."<init>":()V
         4: return
      LineNumberTable:
        line 3: 0
      LocalVariableTable:
        Start  Length  Slot  Name   Signature
            0       5     0  this   Lchapter6/TestClass;

  public int inc();
    descriptor: ()I
    flags: (0x0001) ACC_PUBLIC
    Code:
      stack=2, locals=1, args_size=1
         0: aload_0
         1: getfield      #7                  // Field m:I
         4: iconst_1
         5: iadd
         6: ireturn
      LineNumberTable:
        line 8: 0
      LocalVariableTable:
        Start  Length  Slot  Name   Signature
            0       7     0  this   Lchapter6/TestClass;
}
SourceFile: "TestClass.java"
```

#1~#21의 상수 풀 내용 중 소스 코드에서 내가 작성하지 않은 값들이 존재한다.
이 상수들은 컴파일러가 자동으로 생성한 것으로 필드, 메서드, 속성 테이블 등에서 참조한다. 뿐만 아니라 리플렉션 등 기타 편의성을 위해 생성되는 경우도 존재한다.
자바에선 클래스를 무수히 만들 수 있어 u2와 같이 제한된 숫자로 표현할 수 없다. 그렇기에 상수 테이블의 심벌 참조를 참고하는 형태로 표현한다.

# 3. 접근 플래그
상수 풀 다음의 2바이트는 현재 클래스 또는 인터페이스의 접근 정보를 식별하는 접근 플래그(access_flags)다.
-> 클래스, 인터페이스, 추상 클래스, public 등을 표현

접근 플래그는 u2 타입으로 최대 16개를 사용할 수 있지만 현재는 9개만 정의되어 있다. 정의되지 않은 플래그 비트의 값은 모두 0이다.
TestClass는 public이며, 1.2버전 이상을 사용했으므로 ACC_PUBLIC, ACC_SUPER가 존재해야 한다. 
즉, 0x0001 | 0x0020 = 0x0021이 되어야 한다.

# 4. 클래스 인덱스, 부모 클래스 인덱스, 인터페이스 인덱스
접근 플래그 다음엔 클래스 인덱스, 부모 클래스 인덱스, 인터페이스 인덱스가 나온다. 이 정보들은 클래스 파일의 상속 관계를 규정한다.
앞의 두 인덱스는 u2 타입이며, 세 번째는 컬렉션으로 u2 타입의 묶음이다.
-> 자바에서 다중 상속을 지원하지 않지만 인터페이스는 여러 개를 구현할 수 있음

클래스 인덱스, 부모 클래스 인덱스의 값은 CONSTANT_Class_info 타입의 클래스 서술자 상수를 가리킨다.
인터페이스 인덱스 컬렉션의 경우 첫 항목엔 u2 타입으로 현재 클래스가 구현한 인터페이스의 수를 보여준다. 
구현된 인터페이스가 존재하지 않는다면 값은 0이고, 존재한다면 implements 뒤에 나열된 인터페이스의 개수를 표현한다.

# 5. 필드 테이블
필드 테이블은 인터페이스나 클래스 안에 선언된 변수들을 설명하는데 사용된다.
-> 클래스 변수, 인스턴스 변수를 의미하며, 메서드 내의 변수들을 의미하지 않음

필드가 담을 수 있는 다음과 같은 정보를 표현한다.
- 접근 제한자(public, protected, private)
- 인스턴스 변수와 클래스 변수 구분(static)
- 불변 여부(final)
- 휘발성(volatile)
- 직렬화 포함 여부(transient)
- 데이터 타입(기본형, 참조형, 배열)
- 필드 이름

```text
field_info {
	u2　　　      　　　access_flags; // 클래스의 access_flags와 유사함
	u2　　　　　　　　　name_indx; // 상수 풀의 인덱스로 필드의 단순 이름을 참조
	u2　　　　　　　　　descriptor_index; // 상수 풀의 인덱스로 필드 및 메서드의 서술자를 참조
	u2　　　　　　　　　attributes_count;
	attribute_info　　　attributes[attributes_count];
}
```

>[!NOTE]
>**단순 이름** - 메서드나 필드 이름을 참조할 때 이용하며 타입과 매개 변수 정보가 생략된 형태
>**완전한 이름** - 패키지 경로과 클래스 이름을 포함한 전체 경로에서 .을 /로 바꾼 값
>**서술자** - 필드의 경우엔 데이터 타입까지, 메서드의 경우엔 매개 변수 목록과 반환 값까지 기술
>서술자에서 기본 데이터 타입은 B, C, D 등 대문자로 표현하며 참조형은 L로 표현한다. 배열 타입은 \[를 붙여 표현하며, 다차원 배열인 경우 차원 수만큼 \[를 추가
>
>**예시**
>void inc() -> "()V"
>int indexOf(char[] source, int sourceOffset, int sourceCount, char[] target, int targetOffset, int targetCount, int fromIndx) -> "\([CII[CIII)I"

![[JVM 6장 - 필드 테이블 구조.png]]

필드 테이블에 반드시 포함되어야 하는 데이터 항목은 decriptor_index까지다. 이 뒤로는 코드에 따라 속성 테이블 컬렉션이 따라온다. 
이때, 부모 클래스나 부모 인터페이스로부터 상속받은 필드는 필드 테이블 컬렉션에 나열하지 않는다. 

# 6. 메서드 테이블
```text
field_info {
	u2　　　      　　　access_flags
	u2　　　　　　　　　name_indx; 
	u2　　　　　　　　　descriptor_index;
	u2　　　　　　　　　attributes_count;
	attribute_info　　　attributes[attributes_count];
}
```
메서드 테이블의 구조는 필드 테이블과 완전히 같다. 각 타입이 의미하는 바도 같다.
다만 이를 통해 표현할 수 있는 것은 메서드 정의뿐이다. 메서드의 본문, 즉 구현부는 표현되지 않는다. 

메서드 본문의 코드는 바이트 코드 명령어로 변환된 후, 메서드 속성 테이블 컬렉션의 Code 속성으로 저장된다.
![[JVM 6장 - 메서드 테이블 구조.png]]
마지막 attribute_name_index의 값은 0x000D인데 해당하는 상수는 Code다. 
처음에 표현된는 0x0002는 method_count의 값인데 우리가 정의한 메서드는 1개 뿐이다. 
이는 컴파일러가 자동으로 메소드를 추가할 수 있기 때문이다. 여기선 인스턴스 생성자인 "\<init>()"이 추가되었다. 이 외에 클래스 생성자인 \<cinit>()도 추가될 수 있다.

# 7. 속성 테이블
속성 테이블은 클래스 파일, 필드 테이블, 메서드 테이블, Code 속성 등 모두 **특정 시나리오에서 특정한 정보를 설명하기 위해 고유한 속성 테이블을 포함**할 수 있다.
클래스 파일의 다른 데이터 항목들은 순서, 길이, 내용을 엄격하게 지켜야하는데 반해 속성 테이블 컬렉션은 그렇지 않다.
JDK 21기준 총 30개의 속성이 존재하며,  기존 속성과 중복되지 않는 한 새로운 속성 정보를 테이블에 추가할 수 있다. 다만 JVM이 인식하지 못하는 속성은 무시된다.
자세한 속성 목록은 312p를 참조

속성 이름은 모두 CONSTANT_Utf8 타입 상수를 참조해 표현하며, 속성 값의 길이는 u4 타입으로 표현한다. 
구조는 완벽하게 사용자 정의할 수 있으며 지켜야할 공통 구조는 아래와 같다.
```text
attribute_info {
	u2　attribute_name_index;
	u4　attribute_length;
	u1　info[attribute_length;
}
```

## Code 속성
앞서 말했듯 메서드의 본문은 바이트 코드로 변환된 후에 Code 속성에 저장된다. 
추상 메서드의 경우엔 본문이 없으므로 Code속성이 존재하지 않는다. 

Code 속성의 구조는 다음과 같다.
```text
Code_attribute {
	u2　attribute_name_inext; 　// 속성 이름을 가리키는 상수의 인덱스
	u4　attribute_length;　　 　// 속성의 길이
	u2　max_stack;　　　　　　　// 피연산자 스택의 최대 깊이(메서드 실행 중엔 이 깊이를 절대 넘을 수 없음)
	u2　max_locals;　　　　　　 // 지역 변수 테이블에 필요한 저장소 공간(단위가 변수 슬롯임에 주의 - 슬롯 하나는 4바이트), 매개변수, 예외 매개 변수, 지역 변수 모두 저장됨
	u4　code_length;　　　　　　// 바이트 코드 스트림 길이
	u1　code[code_length];　　　// 바이트 코드 스트림 
	u2　exception_table_length; // 예외 테이블 길이
	{　u2　start_pc;　　　　　　
	　 u2　end_pc;
	　 u2　handler_pc;
	　 u2　catch_type;
	} exception_table[exception_table_length];
	u2　attributes_count;
	attribute_info attributes[attributes_count];
}
```

피연산자 스택과 지역 변수 테이블은 메서드 스택 프레임의 메모리 사용량에 직접적인 영향을 준다.
그러므로 피연산자 스택의 깊이와 변수 슬롯의 개수를 필요 이상으로 잡을 경우 메모리가 낭비된다. 그래서 JVM은 사용을 마친 변수 슬롯을 재사용한다.
실행 코드가 지역 변수의 유효 범위를 벗어나면 그 변수가 차지하던 슬롯을 다른 변수가 사용하도록 한다.
이 때, 자바 컴파일러는 변수의 유효범위를 참고해 변수별로 적합한 변수 슬롯을 할당한 뒤 **동시에 존재하는 지역 변수들이 차지하는 슬롯의 최대 개수를 max_locals의 크기로 잡는다.**

u4 타입의 code_length는 이론상 2의 32승만큼 크기를 가질 수 있다. 하지만 자바 가상 명세에는 이 값이 65535를 넘을 수 없다고 명시한다.
그러므로 사실상 u2 타입에 해당되며, 이 크기를 넘을 경우 컴파일이 안된다.

### VM이 바이트 코드 영역을 읽는 과정

![[JVM 6장 - Code 속성 예시.png]]
![[JVM 6장 - 바이트 코드 예시.png|300]]
1. 2A를 읽고 바이트 코드 명령어 테이블에서 0x2A에 해당하는 명령어를 찾는다. 
   결과는 aload_0이며 0번째 슬롯에 담긴 참조 타입 지역 변수를 피연산자 스택의 맨 위로 읽어 들이라는 뜻이다.
2. B7에 해당하는 명령어를 찾는다. invokespecial이며 이 명령어는 스택 가장 위의 참조 타입 데이터가 가리키는 
   객체를 메서드의 수신자(receiver)로 사용해 해당 객체의 인스턴스 생성자나 private 메서드 또는 상위 클래스의 메서드를 호출한다.
3. invokespecial 명령에 딸린 매개변수 00 01을 읽는다. 
4. B1에 해당하는 명령어를 읽어 return 한다.
상세한 내용은 7~8장을 통해 더 알 수 있다.

아래는 javap로 바이트 코드를 분석한 결과 중 Code 부분이다.
여기서 생성자의 args_size=1인 것은 this 키워드 때문이다. 
자바 컴파일러가 소스 코드를 컴파일 할 때 this 키워드를 이용하는 코드를 발견하면 일반적인 메서드 매개 변수를 통해 접근하는 코드로 변환한다. static 메서드인 경우는 그렇지 않다.
```text
{
  public chapter6.TestClass();
    descriptor: ()V
    flags: (0x0001) ACC_PUBLIC
    Code:
      stack=1, locals=1, args_size=1 // 자바가 암묵적으로 제공하는 기능으로 this 키워드를 의미
         0: aload_0
         1: invokespecial #1                  // Method java/lang/Object."<init>":()V
         4: return
      LineNumberTable:
        line 3: 0
      LocalVariableTable:
        Start  Length  Slot  Name   Signature
            0       5     0  this   Lchapter6/TestClass;

  public int inc();
    descriptor: ()I
    flags: (0x0001) ACC_PUBLIC
    Code:
      stack=2, locals=1, args_size=1
         0: aload_0
         1: getfield      #7                  // Field m:I
         4: iconst_1
         5: iadd
         6: ireturn
      LineNumberTable:
        line 8: 0
      LocalVariableTable:
        Start  Length  Slot  Name   Signature
            0       7     0  this   Lchapter6/TestClass;
}
SourceFile: "TestClass.java"
```

### Code 속성의 예외 테이블
바이트 코드 명령어 뒤에는 해당 메서드와 관련한 명시적 예외 처리 테이블 집합이 나오는데 필수는 아니다. 

```text
u2　exception_table_length; // 예외 테이블 길이
	{　u2　start_pc;　　　　　　
	　 u2　end_pc;
	　 u2　handler_pc;
	　 u2　catch_type;
	} exception_table[exception_table_length];
```
start_pc와 end_pc줄 사이에서 catch_type 또는 그 하위 예외가 발생하면 handler_pc줄로 이동하라는 뜻이다. 
catch_type이 0이면 어떤 비정상 상황이 발생하든 handler_pc로 이동해야 한다는 뜻이다.

// TODO :: 예외 테이블 동작 시연 추가로 작성

## Exceptions 속성
앞선 Code 속성과 같은 레벨이며 Code 속성의 예외 테이블과 혼동해선 안된다. 
Exception 속성은 throws 뒤에 나오는 checked exception을 가리킨다.

## LineNumberTable 속성
자바 소스 코드의 줄 번호와 바이트코드의 줄 번호 사이의 대응 관계를 설명하는 속성이다. 
필수적인 속성은 아니지만 사용하지 않는다면 예외 발생시 코드의 줄 번호가 스택 트레이스에 나타나지 않는다.
또한 디버깅 할 때 자바 소스 특정 줄에 중단점을 설정할 수 없다.

## LocalVariableTable, LocalVariableTypeTable 속성
LocalVariableTable은 스택 프레임에 존재하는 지역 변수 테이블 안의 변수와 소스 코드에 정의된 변수 사이의 관계를 설명하는 속성이다. 
이 또한 필수 속성은 아니지만 사용하지 않는다면 다른 사람이 이 메서드를 참조할 때 매개 변수 이름을 알 수 없어 맥락 파악이 어려워진다.

LocalVariableTypeTable는 JDK5에 제네릭이 도입되면서 추가된 LocalVariableTable의 자매 속성이다. 
자바의 제네릭은 소거법을 사용하는데 이를 보완하기 위해 추가되었다.

## SourceFile과 SourceDebugExtension 속성
SoureFile 속성에는 클래스 파일을 생성한 자바 소스 파일 이름이 기록된다.
이 속성도 선택 사항이며 설정하지 않는 경우 내부 클래스와 같은 특수한 경우는 예외 발생시 스택 트레이스에 정보가 남지 않는다. 
SourceDebugExtension은 JSP에서 디버깅을 하기 위함이다.

## ConstantValue 속성
정적 변수에 값을 자동으로 할당하도록 VM에게 알린다. static 키워드로 선언된 변수에만 이 속성이 붙는다.
인스턴스 변수 할당은 인스턴스 생성자인 \<init>() 에서 수행한다. 하지만 클래스 변수는 \<clinit>()을 사용하거나 ConstantValue 속성을 사용해야 한다.
현재 오라클이 구현한 javac 컴파일러는 final static 변수 중 기본형 또는 String인 경우엔 ConstantValue를 사용해 초기화 하고, 
final이 아니거나 기본형, String이 아닌 경우엔 \<clinit>()으로 초기화 한다.
ConstantValue의 속성 값이 기본형과 String으로 제한되는 것은 이 속성의 값이 상수 풀의 인덱스 번호일 뿐이고, 
클래스 파일 형식의 상수 타입에는 기본형에 해당하는 리터럴과 문자열마나 존재하기 때문이다.

## InnerClass 속성
내부 클래스와 호스트 클래스 사이의 연결 관계를 기록한다. 내부 클래스를 정의하면 컴파일러가 자동으로 해당 속성을 생성한다.

## Deprecated, Synthetic 속성
두 속성 모두 Boolean 속성이다. 
Deprecated는 필드 또는 메서드 폐기 대상 여부를 의미하고, Synthetic 속성은 컴파일러가 추가한 필드나 메서드임을 나타내는 속성이다. 

## StackMapTable 속성
JDK 6 때 클래스 파일 명세에 추가 되었으며, Code 속성의 attributes 테이블에 자리하는 상당히 복잡한 가변 길이 속성이다. 
이 속성은 VM이 클래스를 로드할 때 바이트코드 검증 단계에서 타입 검증기가 활용한다.

기존 바이트 코드 검증 단계의 성능을 개선하기 위해 나온 속성이며 자세한 내용은 7장에 서술된다.

## Signature 속성
JDK 5 때 제네릭을 지원하기 위해 추가된 속성이며, 클래스의 속성 테이블, 필드 테이블, 메서드 테이블에 선택적으로 등장할 수 있다.
